qrate/__init__.py
qrate/analyze.py
qrate/db.py
qrate/export.py
qrate/group.py
qrate/ingest.py
qrate/score.py
qrate-0.1.1.dist-info/METADATA
qrate-0.1.1.dist-info/WHEEL
qrate-0.1.1.dist-info/entry_points.txt
qrate-0.1.1.dist-info/licenses/LICENSE
qrate-0.1.1.dist-info/RECORD
