Metadata-Version: 2.4
Name: qrate
Version: 0.1.1
Summary: Image curation tool
Project-URL: Repository, https://github.com/swap357/qrate
Author: swap357
License: MIT
License-File: LICENSE
Requires-Python: >=3.11
Requires-Dist: blake3>=0.4
Requires-Dist: imagehash>=4.3
Requires-Dist: numpy>=1.24
Requires-Dist: pillow>=10.0
Requires-Dist: rawpy>=0.18
Requires-Dist: rich>=13.0
Provides-Extra: cv
Requires-Dist: opencv-python-headless>=4.8; extra == 'cv'
Provides-Extra: dev
Requires-Dist: mypy>=1.5.0; extra == 'dev'
Requires-Dist: pytest-cov>=4.0; extra == 'dev'
Requires-Dist: pytest>=7.0; extra == 'dev'
Requires-Dist: ruff>=0.1.0; extra == 'dev'
